image_processing/__init__.py
image_processing/processing/__init__.py
image_processing/processing/combination.py
image_processing/processing/transformation.py
image_processing/utils/__init__.py
image_processing/utils/io.py
image_processing/utils/plot.py
image_processing_nferepa01/__init__.py
image_processing_nferepa01/processing/__init__.py
image_processing_nferepa01/processing/combination.py
image_processing_nferepa01/processing/transformation.py
image_processing_nferepa01/utils/__init__.py
image_processing_nferepa01/utils/io.py
image_processing_nferepa01/utils/plot.py
image_processing_nferepa01-0.0.1.dist-info/METADATA
image_processing_nferepa01-0.0.1.dist-info/WHEEL
image_processing_nferepa01-0.0.1.dist-info/top_level.txt
image_processing_nferepa01-0.0.1.dist-info/RECORD
