Metadata-Version: 2.1
Name: image-processing-nferepa01
Version: 0.0.1
Summary: Image Processing Package using Skimage
Home-page: https://github.com/NicholasPaiva0/image-processing-package
Author: Nicholas e Karina
Requires-Python: >=3.5
Requires-Dist: matplotlib
Requires-Dist: numpy
Requires-Dist: scikit-image>=0.16.1
